statsframe/__init__.py
statsframe/_databackend.py
statsframe/_tbl_data.py
statsframe/datasummary.py
statsframe-0.0.3.dist-info/LICENSE
statsframe-0.0.3.dist-info/METADATA
statsframe-0.0.3.dist-info/WHEEL
statsframe-0.0.3.dist-info/RECORD
